saxspy.py
saxs_analysis-1.0.2.dist-info/LICENSE
saxs_analysis-1.0.2.dist-info/METADATA
saxs_analysis-1.0.2.dist-info/WHEEL
saxs_analysis-1.0.2.dist-info/top_level.txt
saxs_analysis-1.0.2.dist-info/RECORD
