Metadata-Version: 2.1
Name: saxs-analysis
Version: 1.0.2
Summary: SAXS python package
Home-page: https://github.com/emathew16/SAXS_analysis
Author: Elizabeth Mathew
Author-email: Elizabeth.Mathew@hereon.de
License: UNKNOWN
Platform: UNKNOWN
Classifier: Programming Language :: Python :: 3
Classifier: License :: OSI Approved :: MIT License
Classifier: Operating System :: OS Independent
License-File: LICENSE
